GitHubHealth/__init__.py
GitHubHealth/main.py
GitHubHealth/requested_object.py
GitHubHealth/utils.py
GitHubHealth/app/.dockerignore
GitHubHealth/app/.gcloudignore
GitHubHealth/app/Dockerfile
GitHubHealth/app/app.yaml
GitHubHealth/app/forms.py
GitHubHealth/app/main.py
GitHubHealth/app/requirements.txt
GitHubHealth/app/static/favicon.ico
GitHubHealth/app/static/assets/apple-touch-icon.png
GitHubHealth/app/static/assets/arrow-left-circle-fill.svg
GitHubHealth/app/static/assets/arrow-right-circle-fill.svg
GitHubHealth/app/static/assets/banner.png
GitHubHealth/app/static/assets/clipboard.svg
GitHubHealth/app/static/assets/clippy.svg
GitHubHealth/app/static/assets/loadingimage.gif
GitHubHealth/app/static/assets/moon.svg
GitHubHealth/app/static/assets/person-fill.svg
GitHubHealth/app/static/assets/search.svg
GitHubHealth/app/static/assets/sun.svg
GitHubHealth/app/static/assets/wheel.png
GitHubHealth/app/static/css/main.css
GitHubHealth/app/static/scripts/base.js
GitHubHealth/app/static/scripts/check_theme.js
GitHubHealth/app/static/scripts/plots.js
GitHubHealth/app/static/scripts/snippets.js
GitHubHealth/app/static/scripts/tooltips.js
GitHubHealth/app/templates/about.html
GitHubHealth/app/templates/base.html
GitHubHealth/app/templates/images.html
GitHubHealth/app/templates/index.html
GitHubHealth/app/templates/repo_status.html
GitHubHealth/app/templates/search_results.html
GitHubHealth/app/templates/status.html
GitHubHealth/app/templates/test_repo_status.html
GitHubHealth/app/templates/user.html
data/pylint.svg
GitHubHealth-0.0.0.1641127350.dist-info/LICENSE
GitHubHealth-0.0.0.1641127350.dist-info/METADATA
GitHubHealth-0.0.0.1641127350.dist-info/WHEEL
GitHubHealth-0.0.0.1641127350.dist-info/top_level.txt
GitHubHealth-0.0.0.1641127350.dist-info/RECORD
