Metadata-Version: 2.1
Name: GitHubHealth
Version: 0.0.0.1641127350
Summary: GitHubHealth is a Python library for monitoring code health in GitHub.
Home-page: https://github.com/ckear1989/github/
Author: Conor Kearney
Author-email: ckear1989@gmail.com
License: MIT
Platform: UNKNOWN
License-File: LICENSE
Requires-Dist: PyGitHub (==1.55)
Requires-Dist: pandas (==1.3.4)
Requires-Dist: flask (==2.0.2)
Requires-Dist: flask-wtf (==1.0.0)
Requires-Dist: Flask-Bootstrap4 (==4.0.2)
Requires-Dist: altair (==4.1.0)
Requires-Dist: setuptools-scm (>=6.3.2)
Provides-Extra: deploy
Requires-Dist: PyGitHub (==1.55) ; extra == 'deploy'
Requires-Dist: pandas (==1.3.4) ; extra == 'deploy'
Requires-Dist: flask (==2.0.2) ; extra == 'deploy'
Requires-Dist: flask-wtf (==1.0.0) ; extra == 'deploy'
Requires-Dist: Flask-Bootstrap4 (==4.0.2) ; extra == 'deploy'
Requires-Dist: altair (==4.1.0) ; extra == 'deploy'
Requires-Dist: gunicorn (==20.1.0) ; extra == 'deploy'
Provides-Extra: dev
Requires-Dist: pre-commit (>=2.15.0) ; extra == 'dev'
Requires-Dist: PyGitHub (>=1.55) ; extra == 'dev'
Requires-Dist: pylint (>=2.11.1) ; extra == 'dev'
Requires-Dist: pandas (>=1.3.4) ; extra == 'dev'
Requires-Dist: flask (>=2.0.2) ; extra == 'dev'
Requires-Dist: flask-wtf (>=1.0.0) ; extra == 'dev'
Requires-Dist: Flask-Bootstrap4 (>=4.0.2) ; extra == 'dev'
Requires-Dist: altair (>=4.1.0) ; extra == 'dev'
Requires-Dist: gunicorn (>=20.1.0) ; extra == 'dev'
Requires-Dist: anybadge (>=1.8.0) ; extra == 'dev'
Provides-Extra: test
Requires-Dist: pytest (>=6.2.5) ; extra == 'test'
Requires-Dist: subx (>=2020.42.0) ; extra == 'test'
Requires-Dist: docutils (>=0.18) ; extra == 'test'
Requires-Dist: pytest-codeblocks (>=0.12.0) ; extra == 'test'
